README.md
setup.py
bitcoin.sh.egg-info/PKG-INFO
bitcoin.sh.egg-info/SOURCES.txt
bitcoin.sh.egg-info/dependency_links.txt
bitcoin.sh.egg-info/not-zip-safe
bitcoin.sh.egg-info/top_level.txt
bitcoin/sh/__init__.py