Metadata-Version: 1.0
Name: bitcoin.sh
Version: 0.1
Summary: bitcoin.sh
Home-page: https://github.com/desantis/python-bitcoin.sh
Author: Andrew T. DeSantis
Author-email: atd@deos.org
License: MIT
Platform: UNKNOWN
